cstx/README.md
cstx/model.py
cstx/utils.py
cstx-0.1.0.dist-info/LICENSE
cstx-0.1.0.dist-info/WHEEL
cstx-0.1.0.dist-info/METADATA
cstx-0.1.0.dist-info/RECORD
